setup.py
lib/evasion/__init__.py
lib/evasion/agency/__init__.py
lib/evasion/agency/agency.py
lib/evasion/agency/agent.py
lib/evasion/agency/manager.py
lib/evasion/agency/utils.py
lib/evasion/agency/agents/__init__.py
lib/evasion/agency/agents/base/__init__.py
lib/evasion/agency/agents/base/service.py
lib/evasion/agency/agents/testing/__init__.py
lib/evasion/agency/agents/testing/fake.py
lib/evasion/agency/agents/tests/__init__.py
lib/evasion/agency/tests/__init__.py
lib/evasion/agency/tests/testagency.py
lib/evasion_agency.egg-info/PKG-INFO
lib/evasion_agency.egg-info/SOURCES.txt
lib/evasion_agency.egg-info/dependency_links.txt
lib/evasion_agency.egg-info/eager_resources.txt
lib/evasion_agency.egg-info/namespace_packages.txt
lib/evasion_agency.egg-info/not-zip-safe
lib/evasion_agency.egg-info/requires.txt
lib/evasion_agency.egg-info/top_level.txt
scripts/manager