Metadata-Version: 1.0
Name: evasion-agency
Version: 1.1.5
Summary: This provides the hardware abstraction layer communicated with via the event system
Home-page: http://github.com/oisinmulvihill/evasion-agency/tarball/master#egg=evasion_agency
Author: Oisin Mulvihill
Author-email: oisinmulvihill at gmail dot com
License: Evasion Project CDDL License
Platform: UNKNOWN
